iluvatar/__init__.py
iluvatar/iluvatar.py
iluvatar/music_downloader.py
iluvatar-0.0.1.dist-info/METADATA
iluvatar-0.0.1.dist-info/WHEEL
iluvatar-0.0.1.dist-info/top_level.txt
iluvatar-0.0.1.dist-info/RECORD
