Metadata-Version: 2.1
Name: iluvatar
Version: 0.0.1
Summary: With each note, Eru crafts worlds, blending music and magic into stunning realities.
Author-email: Rafael dos Reis <rreis@kuma.ninja>
Project-URL: Homepage, https://github.com/kuma-ninja/iluvatar
Classifier: Programming Language :: Python :: 3
Classifier: License :: OSI Approved :: MIT License
Classifier: Operating System :: OS Independent
Requires-Python: >=3.12
Requires-Dist: audioread ==3.0.1
Requires-Dist: Brotli ==1.1.0
Requires-Dist: cachetools ==5.5.0
Requires-Dist: certifi ==2024.8.30
Requires-Dist: cffi ==1.17.1
Requires-Dist: charset-normalizer ==3.3.2
Requires-Dist: decorator ==5.1.1
Requires-Dist: google-api-core ==2.20.0
Requires-Dist: google-api-python-client ==2.147.0
Requires-Dist: google-auth ==2.35.0
Requires-Dist: google-auth-httplib2 ==0.2.0
Requires-Dist: googleapis-common-protos ==1.65.0
Requires-Dist: httplib2 ==0.22.0
Requires-Dist: idna ==3.10
Requires-Dist: joblib ==1.4.2
Requires-Dist: lazy-loader ==0.4
Requires-Dist: librosa ==0.10.2.post1
Requires-Dist: llvmlite ==0.43.0
Requires-Dist: msgpack ==1.1.0
Requires-Dist: mutagen ==1.47.0
Requires-Dist: numba ==0.60.0
Requires-Dist: numpy ==2.0.2
Requires-Dist: packaging ==24.1
Requires-Dist: pandas ==2.2.3
Requires-Dist: platformdirs ==4.3.6
Requires-Dist: pooch ==1.8.2
Requires-Dist: proto-plus ==1.24.0
Requires-Dist: protobuf ==5.28.2
Requires-Dist: pyasn1 ==0.6.1
Requires-Dist: pyasn1-modules ==0.4.1
Requires-Dist: pycparser ==2.22
Requires-Dist: pycryptodomex ==3.20.0
Requires-Dist: pyparsing ==3.1.4
Requires-Dist: python-dateutil ==2.9.0.post0
Requires-Dist: python-dotenv ==1.0.1
Requires-Dist: pytz ==2024.2
Requires-Dist: requests ==2.32.3
Requires-Dist: rsa ==4.9
Requires-Dist: scikit-learn ==1.5.2
Requires-Dist: scipy ==1.14.1
Requires-Dist: six ==1.16.0
Requires-Dist: soundfile ==0.12.1
Requires-Dist: soxr ==0.5.0.post1
Requires-Dist: threadpoolctl ==3.5.0
Requires-Dist: typing-extensions ==4.12.2
Requires-Dist: tzdata ==2024.2
Requires-Dist: uritemplate ==4.1.1
Requires-Dist: urllib3 ==2.2.3
Requires-Dist: websockets ==13.1
Requires-Dist: yt-dlp ==2024.8.6
